setup.py
packageDIY/__init__.py
packageDIY/__version__.py
packageDIY/aaaaa.py
packageDIY/appiumTest.py
packageDIY/crawl_dealwith_post_auto.py
packageDIY/run_auto_comment.py
packageDIY/run_auto_contentImgs.py
packageDIY/run_auto_keyParagraph.py
packageDIY/run_auto_relativeParagraph.py
packageDIY/run_auto_selenium.py
packageDIY/run_auto_thumbnailImgs.py
packageDIY/run_auto_video.py
packageDIY.egg-info/PKG-INFO
packageDIY.egg-info/SOURCES.txt
packageDIY.egg-info/dependency_links.txt
packageDIY.egg-info/top_level.txt
packageDIY/articlesRef/__init__.py
packageDIY/articlesRef/Cleaner/Cleaner.py
packageDIY/articlesRef/Cleaner/__init__.py
packageDIY/articlesRef/DatabaserOperator/__init__.py
packageDIY/articlesRef/DatabaserOperator/databaseOperator.py
packageDIY/articlesRef/Filter/Filter.py
packageDIY/articlesRef/Filter/__init__.py
packageDIY/articlesRef/Poster/Poster.py
packageDIY/articlesRef/Poster/__init__.py
packageDIY/articlesRef/universalTools/__init__.py
packageDIY/articlesRef/universalTools/tools.py
packageDIY/commentsRef/__init__.py
packageDIY/commentsRef/Cleaner/Cleaner.py
packageDIY/commentsRef/Cleaner/__init__.py
packageDIY/commentsRef/DatabaserOperator/__init__.py
packageDIY/commentsRef/DatabaserOperator/databaseOperator.py
packageDIY/commentsRef/Filter/Filter.py
packageDIY/commentsRef/Filter/__init__.py
packageDIY/commentsRef/Poster/Poster.py
packageDIY/commentsRef/Poster/__init__.py
packageDIY/commentsRef/universalTools/__init__.py
packageDIY/commentsRef/universalTools/tools.py
packageDIY/globalTools/__init__.py
packageDIY/globalTools/douyinCrack.py
packageDIY/globalTools/globalTools.py
packageDIY/globalTools/sliderCheck.py
packageDIY/imagesRef/__init__.py
packageDIY/imagesRef/Classifier/Classifier.py
packageDIY/imagesRef/Classifier/__init__.py
packageDIY/imagesRef/DatabaserOperator/__init__.py
packageDIY/imagesRef/DatabaserOperator/databaseOperator.py
packageDIY/imagesRef/Filter/Filter.py
packageDIY/imagesRef/Filter/__init__.py
packageDIY/imagesRef/Poster/Poster.py
packageDIY/imagesRef/Poster/__init__.py
packageDIY/imagesRef/Processing/Processing.py
