Metadata-Version: 2.1
Name: packageDIY
Version: 0.0.10
Summary: 用于爬取段落数据、图片数据、视频数据以及处理上传等
Home-page: https://github.com/Tommy-pixels/packageDIY
Author: 唐国钦
Author-email: dreamertgq@163.com
License: UNKNOWN
Platform: UNKNOWN
Classifier: Programming Language :: Python :: 3
Classifier: License :: OSI Approved :: MIT License
Classifier: Operating System :: OS Independent
Requires-Python: >=3.6.8
